time_robust_forest/__init__.py
time_robust_forest/__main__.py
time_robust_forest/functions.py
time_robust_forest/hyper_opt.py
time_robust_forest/models.py
time_robust_forest/py.typed
time_robust_forest-0.1.14.dist-info/entry_points.txt
time_robust_forest-0.1.14.dist-info/LICENSE
time_robust_forest-0.1.14.dist-info/WHEEL
time_robust_forest-0.1.14.dist-info/METADATA
time_robust_forest-0.1.14.dist-info/RECORD
