Metadata-Version: 2.1
Name: time-robust-forest
Version: 0.1.14
Summary: Explores time information to train a robust random forest
Home-page: https://github.com/lgmoneda/time-robust-forest
License: BSD-3
Author: lgmoneda
Author-email: lgmoneda@gmail.com
Requires-Python: >=3.9.12,<4.0.0
Classifier: Development Status :: 3 - Alpha
Classifier: Intended Audience :: Developers
Classifier: License :: Other/Proprietary License
Classifier: Operating System :: OS Independent
Classifier: Programming Language :: Python :: 3
Classifier: Topic :: Software Development :: Libraries :: Python Modules
Requires-Dist: click (==8.1.3)
Requires-Dist: importlib_metadata (>=1.6,<5.0); python_version <= "3.9.12"
Requires-Dist: numpy (==1.23.0)
Requires-Dist: pandas (==1.1.3)
Requires-Dist: rich (>=9.8.2,<11.0.0)
Requires-Dist: scikit-learn (==1.1.0)
Requires-Dist: typer[all] (>=0.5.0,<0.6.0)
Project-URL: Repository, https://github.com/lgmoneda/time-robust-forest
